sing_box_cli/__init__.py
sing_box_cli/common.py
sing_box_cli/main.py
sing_box_cli/py.typed
sing_box_cli/api/__init__.py
sing_box_cli/api/client.py
sing_box_cli/api/connections.py
sing_box_cli/api/logs.py
sing_box_cli/api/monitor.py
sing_box_cli/api/policy.py
sing_box_cli/api/widget.py
sing_box_cli/bin/nssm.exe
sing_box_cli/config/__init__.py
sing_box_cli/config/config.py
sing_box_cli/config/utils.py
sing_box_cli/service/__init__.py
sing_box_cli/service/manager.py
sing_box_cli-0.1.1.dist-info/METADATA
sing_box_cli-0.1.1.dist-info/WHEEL
sing_box_cli-0.1.1.dist-info/entry_points.txt
sing_box_cli-0.1.1.dist-info/licenses/LICENSE
sing_box_cli-0.1.1.dist-info/RECORD
