Metadata-Version: 2.4
Name: sing-box-cli
Version: 0.1.1
Summary: cross-platform sing-box manager.
Project-URL: Homepage, https://github.com/aittcuszz/sing-box-service
Project-URL: Issues, https://github.com/atticuszz/sing-box-service/issues
Project-URL: documentation, https://atticuszz.github.io/sing-box-service/
Project-URL: Changelog, https://github.com/atticuszz/sing-box-service/blob/main/CHANGELOG.md
Author-email: "A.J.Zeller" <hello@atticux.me>
Maintainer-email: "A.J.Zeller" <hello@atticux.me>
License: MIT License
License-File: LICENSE
Classifier: License :: OSI Approved :: MIT License
Classifier: Programming Language :: Python
Classifier: Programming Language :: Python :: 3 :: Only
Classifier: Programming Language :: Python :: 3.11
Classifier: Programming Language :: Python :: 3.12
Classifier: Programming Language :: Python :: 3.13
Classifier: Programming Language :: Python :: 3.14
Requires-Python: <3.15,>=3.11
Requires-Dist: httpx>=0.28.1
Requires-Dist: plotext>=5.3.2
Requires-Dist: prompt-toolkit>=3.0.50
Requires-Dist: psutil>=6.1.1
Requires-Dist: pydantic>=2.10.6
Requires-Dist: sing-box-bin>=1.12.12
Requires-Dist: typer>=0.15.1
